planqk/__init__.py
planqk/runtime/__init__.py
planqk/runtime/_version.py
planqk/runtime/file.py
planqk/runtime/input.py
planqk/runtime/json.py
planqk/runtime/logging.py
planqk/runtime/main.py
planqk/runtime/response.py
planqk/runtime/string.py
planqk/runtime/user_code.py
planqk_python_template-2.0.3.dist-info/LICENSE
planqk_python_template-2.0.3.dist-info/METADATA
planqk_python_template-2.0.3.dist-info/WHEEL
planqk_python_template-2.0.3.dist-info/top_level.txt
planqk_python_template-2.0.3.dist-info/RECORD
