Metadata-Version: 2.1
Name: planqk-python-template
Version: 2.0.3
Summary: Runtime utilities to boost PlanQK Managed Services.
Home-page: https://gitlab.com/planqk-foss/planqk-python-template
Author: Kipu Quantum GmbH
Author-email: info@kipu-quantum.com
License: apache-2.0
Classifier: Programming Language :: Python :: 3
Classifier: License :: OSI Approved :: Apache Software License
Classifier: Operating System :: OS Independent
Requires-Python: >=3.9
License-File: LICENSE
Requires-Dist: loguru
